CDAL/GLOBAL.py
CDAL/__init__.py
CDAL-1.0.2.dist-info/LICENSE
CDAL-1.0.2.dist-info/METADATA
CDAL-1.0.2.dist-info/WHEEL
CDAL-1.0.2.dist-info/top_level.txt
CDAL-1.0.2.dist-info/RECORD
