Metadata-Version: 2.1
Name: CDAL
Version: 1.0.2
Summary: A small Python library for getting information from the user's computer.
Home-page: 
Author: Matthew Schlauderaff
Author-email: matthew.schlauderaff@gmail.com
License: MIT
Classifier: Intended Audience :: Developers
Classifier: License :: OSI Approved :: MIT License
Classifier: Programming Language :: Python
Classifier: Programming Language :: Python :: 3
Classifier: Programming Language :: Python :: 3.6
Classifier: Programming Language :: Python :: 3.7
Classifier: Programming Language :: Python :: 3.8
Classifier: Programming Language :: Python :: 3.9
Classifier: Operating System :: OS Independent
License-File: LICENSE
